nonebot_plugin_are_you_ok-0.1.0.dist-info/METADATA
nonebot_plugin_are_you_ok-0.1.0.dist-info/WHEEL
nonebot_plugin_are_you_ok/__init__.py
nonebot_plugin_are_you_ok/config.py
nonebot_plugin_are_you_ok-0.1.0.dist-info/RECORD
