Metadata-Version: 2.1
Name: nonebot-plugin-are-you-ok
Version: 0.1.0
Summary: A simple plugin for confirming the status of bot.
Author-Email: shoucandanghehe <wallfjjd@gmail.com>
License: MIT
Requires-Python: >=3.9
Requires-Dist: nonebot2>=2.3.0
Requires-Dist: ruff>=0.4.4; extra == "dev"
Requires-Dist: mypy>=1.10.0; extra == "dev"
Requires-Dist: nonebot-adapter-onebot>=2.4.3; extra == "dev"
Requires-Dist: nonebot2[fastapi]>=2.3.0; extra == "dev"
Provides-Extra: dev
